omnidoc/__init__.py
omnidoc/version.py
omnidoc/adapters/__init__.py
omnidoc/adapters/langchain.py
omnidoc/adapters/llamaindex.py
omnidoc/cli/__init__.py
omnidoc/cli/main.py
omnidoc/core/__init__.py
omnidoc/core/document.py
omnidoc/core/exceptions.py
omnidoc/extractors/__init__.py
omnidoc/extractors/base.py
omnidoc/extractors/archive/__init__.py
omnidoc/extractors/archive/extractor.py
omnidoc/extractors/code/__init__.py
omnidoc/extractors/code/extractor.py
omnidoc/extractors/docx/__init__.py
omnidoc/extractors/docx/extractor.py
omnidoc/extractors/image/__init__.py
omnidoc/extractors/image/extractor.py
omnidoc/extractors/markdown/__init__.py
omnidoc/extractors/markdown/extractor.py
omnidoc/extractors/office/__init__.py
omnidoc/extractors/office/docx.py
omnidoc/extractors/office/pptx.py
omnidoc/extractors/office/spreadsheet.py
omnidoc/extractors/pdf/__init__.py
omnidoc/extractors/pdf/extractor.py
omnidoc/extractors/structured/__init__.py
omnidoc/extractors/structured/json_xml.py
omnidoc/extractors/text/__init__.py
omnidoc/extractors/text/extractor.py
omnidoc/layout/__init__.py
omnidoc/layout/columns.py
omnidoc/layout/detector.py
omnidoc/layout/donut.py
omnidoc/layout/layoutlm.py
omnidoc/layout/ordering.py
omnidoc/layout/tables.py
omnidoc/layout/utils.py
omnidoc/loader/__init__.py
omnidoc/loader/load.py
omnidoc/loader/registry.py
omnidoc/loader/router.py
omnidoc/loader/types.py
omnidoc/ocr/__init__.py
omnidoc/ocr/aws_textract.py
omnidoc/ocr/azure_formrec.py
omnidoc/ocr/base.py
omnidoc/ocr/tesseract.py
omnidoc/output/__init__.py
omnidoc/output/serializer.py
omnidoc/pdf/__init__.py
omnidoc/pdf/detector.py
omnidoc/pdf/invoice_kv.py
omnidoc/pdf/normalize.py
omnidoc/pdf/ocr.py
omnidoc/pdf/ocr_tables.py
omnidoc/pdf/pipeline.py
omnidoc/pdf/streaming_pipeline.py
omnidoc/pdf/tables.py
omnidoc/pdf/text.py
omnidoc/postprocess/__init__.py
omnidoc/postprocess/bullets.py
omnidoc/postprocess/headings.py
omnidoc/postprocess/metric_normalizer.py
omnidoc/postprocess/metrics.py
omnidoc_sdk-0.3.9.dist-info/METADATA
omnidoc_sdk-0.3.9.dist-info/WHEEL
omnidoc_sdk-0.3.9.dist-info/entry_points.txt
omnidoc_sdk-0.3.9.dist-info/top_level.txt
omnidoc_sdk-0.3.9.dist-info/RECORD
